setup.py
elsec/__init__.py
elsec/actions.py
elsec/client.py
elsec/exceptions.py
elsec/help.py
elsec/http.py
elsec/output.py
elsec/parser.py
elsec/templates.py
elsec.egg-info/PKG-INFO
elsec.egg-info/SOURCES.txt
elsec.egg-info/dependency_links.txt
elsec.egg-info/entry_points.txt
elsec.egg-info/top_level.txt
elsec/test/__init__.py
elsec/test/fixture.py
elsec/test/test_actions.py
elsec/test/test_client.py
elsec/test/test_output.py
elsec/test/test_parser.py
elsec/test/units.py