Metadata-Version: 1.1
Name: elsec
Version: 1.0.3
Summary: Elasticsearch interactive command line client
Home-page: https://github.com/mkocikowski/elsec
Author: Mik Kocikowski
Author-email: mkocikowski@gmail.com
License: MIT
Platform: UNKNOWN
Classifier: Development Status :: 4 - Beta
Classifier: Environment :: Console
Classifier: Intended Audience :: Developers
Classifier: Intended Audience :: End Users/Desktop
Classifier: License :: OSI Approved :: MIT License
Classifier: Natural Language :: English
Classifier: Operating System :: POSIX
Classifier: Topic :: Internet :: WWW/HTTP :: Indexing/Search
Classifier: Topic :: Utilities
